chainspotter/__init__.py
chainspotter/chain.py
chainspotter-0.0.25.dist-info/LICENSE
chainspotter-0.0.25.dist-info/METADATA
chainspotter-0.0.25.dist-info/WHEEL
chainspotter-0.0.25.dist-info/top_level.txt
chainspotter-0.0.25.dist-info/RECORD
