Metadata-Version: 2.1
Name: chainspotter
Version: 0.0.25
Summary: Redis Streams wrapper for user-item interaction tracking and fetching
Home-page: https://github.com/uSasha/chainspotter
Author: Alexander Dmitriev
Author-email: sasha.engineer@gmail.com
License: UNKNOWN
Platform: UNKNOWN
Classifier: Programming Language :: Python :: 3
Classifier: License :: OSI Approved :: BSD License
Classifier: Operating System :: OS Independent
